thirteenth/__init__.py
thirteenth/__main__.py
thirteenth/ovo.py
thirteenth/ver.py
thirteenth-0.1.dist-info/LICENSE
thirteenth-0.1.dist-info/METADATA
thirteenth-0.1.dist-info/WHEEL
thirteenth-0.1.dist-info/top_level.txt
thirteenth-0.1.dist-info/RECORD
